envbider/__init__.py
envbider/core.py
envbider-0.1.0a1.dist-info/licenses/LICENSE
tests/__init__.py
tests/test_core.py
tests/test_custom_prefixes.py
tests/test_envbider.py
envbider-0.1.0a1.dist-info/METADATA
envbider-0.1.0a1.dist-info/WHEEL
envbider-0.1.0a1.dist-info/top_level.txt
envbider-0.1.0a1.dist-info/RECORD
