Metadata-Version: 2.4
Name: EnvBider
Version: 0.1.0a1
Summary: A Python library for simplified environment variable management
Home-page: https://github.com/yourusername/EnvBider
Author: Your Name
Author-email: your.email@example.com
Project-URL: Bug Tracker, https://github.com/user/EnvBider/issues
Project-URL: Documentation, https://github.com/user/EnvBider#readme
Project-URL: Source Code, https://github.com/user/EnvBider
Keywords: environment,configuration,env,dotenv,settings
Classifier: Development Status :: 3 - Alpha
Classifier: Programming Language :: Python :: 3
Classifier: Programming Language :: Python :: 3.6
Classifier: Programming Language :: Python :: 3.7
Classifier: Programming Language :: Python :: 3.8
Classifier: Programming Language :: Python :: 3.9
Classifier: Programming Language :: Python :: 3.10
Classifier: Programming Language :: Python :: 3.11
Classifier: License :: OSI Approved :: MIT License
Classifier: Operating System :: OS Independent
Classifier: Intended Audience :: Developers
Classifier: Topic :: Software Development :: Libraries :: Python Modules
Requires-Python: >=3.6
License-File: LICENSE
Dynamic: author
Dynamic: author-email
Dynamic: classifier
Dynamic: description
Dynamic: description-content-type
Dynamic: home-page
Dynamic: keywords
Dynamic: license-file
Dynamic: project-url
Dynamic: requires-python
Dynamic: summary
